COPYING.txt
MANIFEST.in
setup.py
docs/html/faq.html
docs/html/genindex.html
docs/html/index.html
docs/html/introduction.html
docs/html/licenses.html
docs/html/modules.html
docs/html/objects.inv
docs/html/py-modindex.html
docs/html/search.html
docs/html/searchindex.js
docs/html/text_mode.html
docs/html/write_scheduler.html
docs/html/_static/ajax-loader.gif
docs/html/_static/basic.css
docs/html/_static/comment-bright.png
docs/html/_static/comment-close.png
docs/html/_static/comment.png
docs/html/_static/doctools.js
docs/html/_static/down-pressed.png
docs/html/_static/down.png
docs/html/_static/file.png
docs/html/_static/jquery.js
docs/html/_static/minus.png
docs/html/_static/nature.css
docs/html/_static/plus.png
docs/html/_static/pygments.css
docs/html/_static/searchtools.js
docs/html/_static/underscore.js
docs/html/_static/up-pressed.png
docs/html/_static/up.png
docs/html/_static/websupport.js
simso/__init__.py
simso.egg-info/PKG-INFO
simso.egg-info/SOURCES.txt
simso.egg-info/dependency_links.txt
simso.egg-info/requires.txt
simso.egg-info/top_level.txt
simso/configuration/Configuration.py
simso/configuration/GenerateConfiguration.py
simso/configuration/__init__.py
simso/configuration/parser.py
simso/core/CSDP.py
simso/core/Caches.py
simso/core/Job.py
simso/core/JobEvent.py
simso/core/Logger.py
simso/core/Model.py
simso/core/ProcEvent.py
simso/core/Processor.py
simso/core/Scheduler.py
simso/core/SchedulerEvent.py
simso/core/Task.py
simso/core/Timer.py
simso/core/__init__.py
simso/core/results.py
simso/core/etm/ACET.py
simso/core/etm/AbstractExecutionTimeModel.py
simso/core/etm/CacheModel.py
simso/core/etm/FixedPenalty.py
simso/core/etm/WCET.py
simso/core/etm/__init__.py
simso/generator/__init__.py
simso/generator/task_generator.py
simso/schedulers/BF.py
simso/schedulers/CC_EDF.py
simso/schedulers/DP_WRAP.py
simso/schedulers/EDCL.py
simso/schedulers/EDF.py
simso/schedulers/EDF2.py
simso/schedulers/EDF_US.py
simso/schedulers/EDF_mono.py
simso/schedulers/EDHS.py
simso/schedulers/EDZL.py
simso/schedulers/EKG.py
simso/schedulers/EPDF.py
simso/schedulers/ER_PD2.py
simso/schedulers/FP.py
