Metadata-Version: 1.1
Name: simso
Version: 0.8.3
Summary: Simulation of Multiprocessor Real-Time Scheduling with Overheads
Home-page: http://projects.laas.fr/simso/
Author: Maxime Cheramy
Author-email: maxime.cheramy@laas.fr
License: UNKNOWN
Download-URL: https://github.com/MaximeCheramy/simso
Platform: UNKNOWN
Classifier: Programming Language :: Python
Classifier: Programming Language :: Python :: 3
Classifier: License :: OSI Approved
Classifier: Operating System :: OS Independent
Classifier: Topic :: Scientific/Engineering
Classifier: Development Status :: 5 - Production/Stable
